{
	"configurations" : 
	[
		{
			"directories" : 
			[
				{
					"build" : ".",
					"hasInstallRule" : true,
					"jsonFile" : "directory-.-Debug-ded049d7bdf3a46f7700.json",
					"minimumCMakeVersion" : 
					{
						"string" : "3.16"
					},
					"projectIndex" : 0,
					"source" : ".",
					"targetIndexes" : 
					[
						0,
						1,
						2
					]
				}
			],
			"name" : "Debug",
			"projects" : 
			[
				{
					"directoryIndexes" : 
					[
						0
					],
					"name" : "03QSet",
					"targetIndexes" : 
					[
						0,
						1,
						2
					]
				}
			],
			"targets" : 
			[
				{
					"directoryIndex" : 0,
					"id" : "03QSet::@6890427a1f51a3e7e1df",
					"jsonFile" : "target-03QSet-Debug-df871d543cb028db38a2.json",
					"name" : "03QSet",
					"projectIndex" : 0
				},
				{
					"directoryIndex" : 0,
					"id" : "03QSet_autogen::@6890427a1f51a3e7e1df",
					"jsonFile" : "target-03QSet_autogen-Debug-0a8392f622165d440e48.json",
					"name" : "03QSet_autogen",
					"projectIndex" : 0
				},
				{
					"directoryIndex" : 0,
					"id" : "03QSet_autogen_timestamp_deps::@6890427a1f51a3e7e1df",
					"jsonFile" : "target-03QSet_autogen_timestamp_deps-Debug-0eb4538265ff8e186946.json",
					"name" : "03QSet_autogen_timestamp_deps",
					"projectIndex" : 0
				}
			]
		}
	],
	"kind" : "codemodel",
	"paths" : 
	{
		"build" : "/Users/mac/Desktop/BarisCanCoskun/Udemy/Qt-Courses/02Qt6CoreIntermediate/03Section5-Collections/build-03QSet-Qt_6_5_2_for_macOS-Debug",
		"source" : "/Users/mac/Desktop/BarisCanCoskun/Udemy/Qt-Courses/02Qt6CoreIntermediate/03Section5-Collections/03QSet"
	},
	"version" : 
	{
		"major" : 2,
		"minor" : 4
	}
}
